{
    "id": "quefigura1",
    "title": "Figuras Geométricas",
    "description": "",
    "parent": "figuras",
    "style": {
        "backgroundImage": "url(img/bg-math.jpg)",
        "color": "#444"
    },
    "levelStyle": {
        "backgroundColor": "#FFE"
    },
    "optionStyle": {
        "backgroundColor": "#FF8",
        "fontSize": "3em"
    },
    "levels": [
        {
            "label": "Nivel 1",
            "sorted": true
        },
        {
            "label": "Nivel 2",
            "timer": 10
        }
    ],
    "slides": [
      {
        "title": "Circulo",
        "options": [
            {
                "cover": "../img/shapes/circle.svg",
                "audio": "circulo",
                "value": "circle"
            },
            {
                "cover": "../img/shapes/square.svg",
                "audio": "cuadrado",
                "value": "square"
            },
            {
                "cover": "../img/shapes/triangle.svg",
                "audio": "triangulo",
                "value": "triangle"
            },
            {
                "cover": "../img/shapes/rectangle.svg",
                "audio": "rectangulo",
                "value": "rectangle"
            },
            {
                "cover": "../img/shapes/oval.svg",
                "audio": "ovalo",
                "value": "oval"
            },
            {
                "cover": "../img/shapes/diamond.svg",
                "audio": "rombo",
                "value": "diamond"
            }
      ],
        "answer": "circle"
      },
      {
        "title": "Ovalo",
        "options": [
            {
                "cover": "../img/shapes/circle.svg",
                "audio": "circulo",
                "value": "circle"
            },
            {
                "cover": "../img/shapes/square.svg",
                "audio": "cuadrado",
                "value": "square"
            },
            {
                "cover": "../img/shapes/triangle.svg",
                "audio": "triangulo",
                "value": "triangle"
            },
            {
                "cover": "../img/shapes/rectangle.svg",
                "audio": "rectangulo",
                "value": "rectangle"
            },
            {
                "cover": "../img/shapes/oval.svg",
                "audio": "ovalo",
                "value": "oval"
            },
            {
                "cover": "../img/shapes/diamond.svg",
                "audio": "rombo",
                "value": "diamond"
            }
      ],
        "answer": "oval"
      },
      {
        "title": "Triangulo",
        "options": [
            {
                "cover": "../img/shapes/circle.svg",
                "audio": "circulo",
                "value": "circle"
            },
            {
                "cover": "../img/shapes/square.svg",
                "audio": "cuadrado",
                "value": "square"
            },
            {
                "cover": "../img/shapes/triangle.svg",
                "audio": "triangulo",
                "value": "triangle"
            },
            {
                "cover": "../img/shapes/rectangle.svg",
                "audio": "rectangulo",
                "value": "rectangle"
            },
            {
                "cover": "../img/shapes/oval.svg",
                "audio": "ovalo",
                "value": "oval"
            },
            {
                "cover": "../img/shapes/diamond.svg",
                "audio": "rombo",
                "value": "diamond"
            }
      ],
        "answer": "triangle"
      },
      {
        "title": "Rectangulo",
        "options": [
            {
                "cover": "../img/shapes/circle.svg",
                "audio": "circulo",
                "value": "circle"
            },
            {
                "cover": "../img/shapes/square.svg",
                "audio": "cuadrado",
                "value": "square"
            },
            {
                "cover": "../img/shapes/triangle.svg",
                "audio": "triangulo",
                "value": "triangle"
            },
            {
                "cover": "../img/shapes/rectangle.svg",
                "audio": "rectangulo",
                "value": "rectangle"
            },
            {
                "cover": "../img/shapes/oval.svg",
                "audio": "ovalo",
                "value": "oval"
            },
            {
                "cover": "../img/shapes/diamond.svg",
                "audio": "rombo",
                "value": "diamond"
            }
      ],
        "answer": "rectangle"
      },
      {
        "title": "Cuadrado",
        "options": [
            {
                "cover": "../img/shapes/circle.svg",
                "audio": "circulo",
                "value": "circle"
            },
            {
                "cover": "../img/shapes/square.svg",
                "audio": "cuadrado",
                "value": "square"
            },
            {
                "cover": "../img/shapes/triangle.svg",
                "audio": "triangulo",
                "value": "triangle"
            },
            {
                "cover": "../img/shapes/rectangle.svg",
                "audio": "rectangulo",
                "value": "rectangle"
            },
            {
                "cover": "../img/shapes/oval.svg",
                "audio": "ovalo",
                "value": "oval"
            },
            {
                "cover": "../img/shapes/diamond.svg",
                "audio": "rombo",
                "value": "diamond"
            }
      ],
        "answer": "square"
      },
      {
        "title": "Rombo",
        "options": [
            {
                "cover": "../img/shapes/circle.svg",
                "audio": "circulo",
                "value": "circle"
            },
            {
                "cover": "../img/shapes/square.svg",
                "audio": "cuadrado",
                "value": "square"
            },
            {
                "cover": "../img/shapes/triangle.svg",
                "audio": "triangulo",
                "value": "triangle"
            },
            {
                "cover": "../img/shapes/rectangle.svg",
                "audio": "rectangulo",
                "value": "rectangle"
            },
            {
                "cover": "../img/shapes/oval.svg",
                "audio": "ovalo",
                "value": "oval"
            },
            {
                "cover": "../img/shapes/diamond.svg",
                "audio": "rombo",
                "value": "diamond"
            }
      ],
        "answer": "diamond"
      }
    ]
}